{"repo": {"timestamp": 1702027793000}, "packages": {"org.dslul.openboard.inputmethod.latin": {"metadata": {"added": 1702027792000, "categories": ["Apps for iodéOS"], "lastUpdated": 1702027792000, "license": "GPL-3.0", "sourceCode": "https://gitlab.com/iode/os/apps/openboard", "authorName": "iodé Team (forked from Helium314 fork)", "name": {"en-US": "OpenBoard"}, "summary": {"en-US": "iodéOS version of OpenBoard"}, "description": {"en-US": "Small adaptations of OpenBoard fork by Helium314."}, "preferredSigner": "c996daab86a8cd32537749a5ee1dc2f984f29d43f3067d2c0a54bf8bbfab62c0"}, "versions": {"d061641dbcb7c16605382beb434e77c25739d19e450663e9089abdda5f2cff0a": {"added": 1702027792000, "file": {"name": "/OpenBoard-3.apk", "sha256": "d061641dbcb7c16605382beb434e77c25739d19e450663e9089abdda5f2cff0a", "size": 27094430}, "manifest": {"nativecode": ["arm64-v8a"], "versionName": "1.4.5-iode.3", "versionCode": 22, "usesSdk": {"minSdkVersion": 30, "targetSdkVersion": 34}, "signer": {"sha256": ["c996daab86a8cd32537749a5ee1dc2f984f29d43f3067d2c0a54bf8bbfab62c0"]}, "usesPermission": [{"name": "android.permission.READ_USER_DICTIONARY"}, {"name": "android.permission.RECEIVE_BOOT_COMPLETED"}, {"name": "android.permission.VIBRATE"}, {"name": "android.permission.WRITE_USER_DICTIONARY"}, {"name": "android.permission.READ_CONTACTS"}, {"name": "org.dslul.openboard.inputmethod.latin.DYNAMIC_RECEIVER_NOT_EXPORTED_PERMISSION"}]}}}}}}